pyjsonata/pyjsonata.py
pyjsonata/jsonata.cpython-37m-x86_64-linux-gnu.so
pyjsonata/__init__.py
pyjsonata-0.0.1a10.dist-info/top_level.txt
pyjsonata-0.0.1a10.dist-info/METADATA
pyjsonata-0.0.1a10.dist-info/WHEEL
pyjsonata-0.0.1a10.dist-info/RECORD
pyjsonata-0.0.1a10.dist-info/LICENSE
