Metadata-Version: 2.1
Name: pyjsonata
Version: 0.0.1a10
Summary: Python bindings for JSONata
Home-page: https://github.com/qlyoung/pyjsonata
Author: Quentin Young
Author-email: qlyoung@qlyoung.net
License: UNKNOWN
Platform: UNKNOWN
Classifier: Development Status :: 2 - Pre-Alpha
Classifier: Intended Audience :: Developers
Classifier: License :: OSI Approved :: MIT License
Classifier: Programming Language :: Python :: 3
Classifier: Programming Language :: Python :: 3.4
Classifier: Programming Language :: Python :: 3.5
Classifier: Programming Language :: Python :: 3.6
Classifier: Programming Language :: Python :: 3.7
Classifier: Programming Language :: Python :: 3.8
